{"article_info":{"sentences":[{"sentence":"Suddenly the Witch(\u2005\u5973\u5deb\u2005) stepped boldly(\u2005\u5927\u80c6\u5730\u2005) out toward the Lion.","type":"","pic_url":""},{"sentence":"It was coming on, always singing, with a slow, heavy pace.","type":"","pic_url":""},{"sentence":"It was only twelve yards away.","type":"","pic_url":""},{"sentence":"She raised her arm and flung(\u2005\u629b\u51fa\u2005) the iron bar straight at its head.","type":"","pic_url":""},{"sentence":"Nobody, least of all Jadis, could have missed at that range.","type":"","pic_url":""},{"sentence":"The bar struck the Lion fair between the eyes.","type":"","pic_url":""},{"sentence":"It glanced off(\u2005\u51fb\u4e2d\u540e\u5f39\u5f00\u2005) and fell with a thud(\u2005\u7830\u7684\u4e00\u58f0\u2005) in the grass. The Lion came on.","type":"","pic_url":""},{"sentence":"Its walk was neither slower nor faster than before; you could not tell whether it even knew it had been hit.","type":"","pic_url":""},{"sentence":"Though its soft pads(\u2005\u722a\u57ab\u2005) made no noise, you could feel the earth shake beneath their weight.","type":"","pic_url":""},{"sentence":"The Witch(\u2005\u5973\u5deb\u2005) shrieked(\u2005\u5c16\u53eb\u2005) and ran: in a few moments she was out of sight among the trees.","type":"","pic_url":""},{"sentence":"Uncle Andrew turned to do likewise(\u2005\u540c\u6837\u5730\u2005), tripped over a root, and fell flat on his face in a little brook(\u2005\u5c0f\u6eaa\u2005) that ran down to join the river.","type":"","pic_url":""},{"sentence":"The children could not move.","type":"","pic_url":""},{"sentence":"They were not even quite sure that they wanted to.","type":"","pic_url":""},{"sentence":"The Lion paid no attention to them. Its huge red mouth was open, but open in song not in a snarl(\u2005\u5486\u54ee\u2005).","type":"","pic_url":""},{"sentence":"It passed by them so close that they could have touched its mane(\u2005\u9b03\u6bdb\u2005).","type":"","pic_url":""},{"sentence":"They were terribly afraid it would turn and look at them, yet in some queer(\u2005\u5947\u602a\u7684\u2005) way they wished it would.","type":"","pic_url":""},{"sentence":"But for all the notice it took of them they might just as well have been invisible(\u2005\u770b\u4e0d\u89c1\u7684\u2005) and unsmellable(\u2005\u95fb\u4e0d\u5230\u7684\u2005).","type":"","pic_url":""},{"sentence":"When it had passed them and gone a few paces further it turned, passed them again, and continued its march eastward(\u2005\u5411\u4e1c\u5730\u2005).","type":"","pic_url":"http://ali.baicizhan.com/readin/images/9_73_78_20170117170634_25089.jpg"},{"sentence":"Uncle Andrew, coughing and spluttering(\u2005\u7ed3\u7ed3\u5df4\u5df4\u2005), picked himself up(\u2005\u722c\u8d77\u6765\u2005).","type":"","pic_url":""},{"sentence":"\u201cNow, Digory,\u201d he said, \u201cwe\u2019ve got rid of that woman, and the brute(\u2005\u91ce\u517d\u2005) of a lion is gone. Give me your hand and put on your ring at once.\u201d","type":"con_start","pic_url":""},{"sentence":"\u201cKeep off,\u201d said Digory, backing away from him. \u201cKeep clear of him, Polly. Come over here beside me. Now I warn you, Uncle Andrew, don\u2019t come one step nearer, we\u2019ll just vanish(\u2005\u6d88\u5931\u2005).\u201d","type":"con_start","pic_url":""},{"sentence":"\u201cDo what you\u2019re told this minute, sir,\u201d said Uncle Andrew. \u201cYou\u2019re an extremely disobedient(\u2005\u4e0d\u542c\u8bdd\u7684\u2005), ill-behaved little boy.\u201d","type":"con_start","pic_url":""},{"sentence":"\u201cNo fear,\u201d said Digory. \u201cWe want to stay and see what happens. I thought you wanted to know about other worlds. Don\u2019t you like it now you\u2019re here?\u201d","type":"con_start","pic_url":""},{"sentence":"\u201cLike it!\u201d exclaimed(\u2005\u60ca\u547c\u2005) Uncle Andrew. \u201cJust look at the state I\u2019m in. And it was my best coat and waistcoat(\u2005\u897f\u670d\u80cc\u5fc3\u2005), too.\u201d","type":"con_start","pic_url":""},{"sentence":"He certainly was a dreadful(\u2005\u7cdf\u900f\u7684\u2005) sight by now: for of course, the more dressed up you were to begin with,","type":"","pic_url":""},{"sentence":"the worse you look after you\u2019ve crawled(\u2005\u722c\u884c\u2005) out of a smashed(\u2005\u7c89\u788e\u7684\u2005) hansom(\u2005\u53cc\u8f6e\u6709\u7bf7\u9a6c\u8f66\u2005) cab(\u2005\u51fa\u79df\u9a6c\u8f66\u2005) and fallen into a muddy(\u2005\u6d51\u6d4a\u7684\u2005) brook(\u2005\u5c0f\u6eaa\u2005).","type":"","pic_url":""},{"sentence":"\u201cI\u2019m not saying,\u201d he added, \u201cthat this is not a most interesting place.","type":"con","pic_url":""},{"sentence":"If I were a younger man, now\u2014perhaps I could get some lively young fellow to come here first.","type":"con","pic_url":""},{"sentence":"One of those big\u2014game hunters.","type":"con","pic_url":""},{"sentence":"Something might be made of this country.","type":"con","pic_url":""},{"sentence":"The climate is delightful. I never felt such air.","type":"con","pic_url":""},{"sentence":"I believe it would have done me good if\u2014if circumstances(\u2005\u73af\u5883\u2005) had been more favorable. If only we\u2019d had a gun.\u201d","type":"con","pic_url":""},{"sentence":"\u201cGuns be damned(\u2005\u8be5\u6b7b\u7684\u2005),\u201d said the Cabby(\u2005\u9a6c\u8f66\u592b\u2005). \u201cI think I\u2019ll go and see if I can give Strawberry a rub(\u2005\u64e6\u6d17\u2005) down. That horse \u2019as more sense than some humans as I could mention.\u201d","type":"con_start","pic_url":""},{"sentence":"He walked back to Strawberry and began making the hissing(\u2005\u53d1\u51fa\u5636\u5636\u58f0\u7684\u2005) noises that grooms(\u2005\u9a6c\u592b\u2005) make.","type":"","pic_url":""},{"sentence":"\u201cDo you still think that Lion could be killed by a gun?\u201d asked Digory. \u201cHe didn\u2019t mind the iron bar much.\u201d","type":"con_start","pic_url":""},{"sentence":"\u201cWith all her faults,\u201d said Uncle Andrew, \u201cthat\u2019s a plucky(\u2005\u80c6\u5927\u5305\u5929\u7684\u2005) gel(\u2005\u59d1\u5a18\u2005), my boy. It was a spirited thing to do.\u201d","type":"con_start","pic_url":""},{"sentence":"He rubbed(\u2005\u6413\u2005) his hands and cracked(\u2005\u628a...\u634f\u5f97\u5288\u556a\u4f5c\u54cd\u2005) his knuckles(\u2005\u6307\u8282\u2005),","type":"","pic_url":""},{"sentence":"as if he were once more forgetting how the Witch(\u2005\u5973\u5deb\u2005) frightened him whenever she was really there.","type":"","pic_url":""},{"sentence":"\u201cIt was a wicked(\u2005\u90aa\u6076\u7684\u2005) thing to do,\u201d said Polly. \u201cWhat harm had he done her?\u201d","type":"con_start","pic_url":""},{"sentence":"\u201cHullo! What\u2019s that?\u201d said Digory. He had darted(\u2005\u98de\u5954\u2005) forward to examine something only a few yards away. \u201cI say, Polly,\u201d he called back. \u201cDo come and look.\u201d","type":"con_start","pic_url":""},{"sentence":"Uncle Andrew came with her; not because he wanted to see but because he wanted to keep close to the children\u2014there might be a chance of stealing their rings.","type":"","pic_url":""},{"sentence":"But when he saw what Digory was looking at, even he began to take an interest.","type":"","pic_url":""},{"sentence":"It was a perfect little model of a lamp-post, about three feet high but lengthening, and thickening in proportion(\u2005\u6bd4\u4f8b\u2005),","type":"","pic_url":""},{"sentence":"as they watched it; in fact growing just as the trees had grown.","type":"","pic_url":""},{"sentence":"\u201cIt\u2019s alive too\u2014I mean, it\u2019s lit,\u201d said Digory.","type":"con","pic_url":""},{"sentence":"And so it was; though of course, the brightness of the sun made the little flame in the lantern hard to see unless your shadow fell on it.","type":"","pic_url":"http://ali.baicizhan.com/readin/images/9_73_78_20170117170735_23878.jpg"},{"sentence":"\u201cRemarkable, most remarkable,\u201d muttered(\u2005\u5600\u5495\u2005) Uncle Andrew.","type":"con_start","pic_url":""},{"sentence":"\u201cEven I never dreamed of Magic like this. We\u2019re in a world where everything, even a lamp-post, comes to life and grows.","type":"con","pic_url":""},{"sentence":"Now I wonder what sort of seed a lamp-post grows from?\u201d","type":"con","pic_url":""},{"sentence":"\u201cDon\u2019t you see?\u201d said Digory. \u201cThis is where the bar fell\u2014the bar she tore off the lamp-post at home.","type":"con_start","pic_url":""},{"sentence":"It sank into the ground and now it\u2019s coming up as a young lamp-post.\u201d","type":"con","pic_url":""},{"sentence":"(But not so very young now; it was as tall as Digory while he said this.)","type":"","pic_url":""},{"sentence":"\u201cThat\u2019s it! Stupendous(\u2005\u4e86\u4e0d\u8d77\u7684\u2005), stupendous(\u2005\u4e86\u4e0d\u8d77\u7684\u2005),\u201d said Uncle Andrew, rubbing(\u2005\u6413\u2005) his hands harder than ever. \u201cHo, ho! They laughed at my Magic.","type":"con_start","pic_url":""},{"sentence":"That fool of a sister of mine thinks I\u2019m a lunatic(\u2005\u75af\u5b50\u2005).","type":"con","pic_url":""},{"sentence":"I wonder what they\u2019ll say now? I have discovered a world where everything is bursting with life and growth.","type":"con","pic_url":""},{"sentence":"Columbus, now, they talk about Columbus. But what was America to this?","type":"con","pic_url":""},{"sentence":"The commercial(\u2005\u5546\u4e1a\u7684\u2005) possibilities of this country are unbounded(\u2005\u65e0\u9650\u7684\u2005).","type":"con","pic_url":""},{"sentence":"Bring a few old bits of scrap(\u2005\u788e\u7247\u2005) iron here, bury them, and up they come as brand(\u2005\u5d2d\u65b0\u7684\u2005) new railway(\u2005\u94c1\u8def\u2005) engines(\u2005\u706b\u8f66\u5934\u2005), battleships(\u2005\u6218\u5217\u8230\u2005), anything you please.","type":"con","pic_url":""},{"sentence":"They\u2019ll cost nothing, and I can sell them at full prices in England.","type":"con","pic_url":""},{"sentence":"I shall be a millionaire(\u2005\u767e\u4e07\u5bcc\u7fc1\u2005). And then the climate! I feel years younger already. I can run it as a health resort(\u2005\u7597\u517b\u80dc\u5730\u2005).","type":"con","pic_url":""},{"sentence":"A good sanatorium(\u2005\u7597\u517b\u9662\u2005) here might be worth twenty thousand a year.","type":"con","pic_url":""},{"sentence":"Of course I shall have to let a few people into the secret. The first thing is to get that brute(\u2005\u91ce\u517d\u2005) shot.\u201d","type":"con","pic_url":""},{"sentence":"\u201cYou\u2019re just like the Witch(\u2005\u5973\u5deb\u2005),\u201d said Polly. \u201cAll you think of is killing things.\u201d","type":"con_start","pic_url":""},{"sentence":"\u201cAnd then as regards oneself,\u201d Uncle Andrew continued, in a happy dream.","type":"con_start","pic_url":""},{"sentence":"\u201cThere\u2019s no knowing how long I might live if I settled here.","type":"con","pic_url":""},{"sentence":"And that\u2019s a big consideration when a fellow has turned sixty.","type":"con","pic_url":""},{"sentence":"I shouldn\u2019t be surprised if I never grew a day older in this country! Stupendous(\u2005\u4e86\u4e0d\u8d77\u7684\u2005)! The land of youth!\u201d","type":"con","pic_url":""},{"sentence":"\u201cOh!\u201d cried Digory. \u201cThe land of youth! Do you think it really is?\u201d","type":"con_start","pic_url":""},{"sentence":"For of course he remembered what Aunt Letty had said to the lady who brought the grapes, and that sweet hope rushed back upon him.","type":"","pic_url":""},{"sentence":"\u201cUncle Andrew,\u201d he said, \u201cdo you think there\u2019s anything here that would cure Mother?\u201d","type":"con","pic_url":""},{"sentence":"\u201cWhat are you talking about?\u201d said Uncle Andrew. \u201cThis isn\u2019t a chemist\u2019s shop. But as I was saying\u2014\u201d","type":"con_start","pic_url":""},{"sentence":"\u201cYou don\u2019t care twopence(\u2005\u4e00\u70b9\u513f\u2005) about her,\u201d said Digory savagely(\u2005\u731b\u70c8\u62a8\u51fb\u5730\u2005). \u201cI thought you might; after all, she\u2019s your sister as well as my Mother.","type":"con_start","pic_url":""},{"sentence":"Well, no matter. I\u2019m jolly well(\u2005\u5f53\u7136\u2005) going to ask the Lion himself if he can help me.\u201d","type":"con","pic_url":""},{"sentence":"And he turned and walked briskly(\u2005\u8f7b\u5feb\u5730\u2005) away. Polly waited for a moment and then went after him.","type":"","pic_url":""},{"sentence":"\u201cHere! Stop! Come back! The boy\u2019s gone mad,\u201d said Uncle Andrew.","type":"con_start","pic_url":""},{"sentence":"He followed the children at a cautious(\u2005\u8c28\u614e\u7684\u2005) distance behind;","type":"","pic_url":""},{"sentence":"for he didn\u2019t want to get too far away from the green rings or too near the Lion.","type":"","pic_url":""},{"sentence":"In a few minutes Digory came to the edge of the wood and there he stopped.","type":"","pic_url":""},{"sentence":"The Lion was singing still. But now the song had once more changed.","type":"","pic_url":""},{"sentence":"It was more like what we should call a tune(\u2005\u66f2\u5b50\u2005), but it was also far wilder.","type":"","pic_url":""},{"sentence":"It made you want to run and jump and climb. It made you want to shout.","type":"","pic_url":""},{"sentence":"It made you want to rush at other people and either hug them or fight them.","type":"","pic_url":""},{"sentence":"It made Digory hot and red in the face.","type":"","pic_url":""},{"sentence":"It had some effect on Uncle Andrew, for Digory could hear him saying, \u201cA spirited gel(\u2005\u59d1\u5a18\u2005), sir.","type":"","pic_url":""},{"sentence":"It\u2019s a pity about her temper(\u2005\u813e\u6c14\u2005), but a dem fine woman all the same, a dem fine woman.\u201d","type":"","pic_url":""},{"sentence":"But what the song did to the two humans was nothing compared with what it was doing to the country.","type":"","pic_url":""}],"previous":"\u5728\u201c\u865a\u65e0\u201d\u7684\u4e16\u754c\u91cc\uff0c\u5929\u8272\u6e10\u6e10\u53d8\u4eae\uff0cDigory\u4e00\u884c\u4eba\u7ec8\u4e8e\u770b\u89c1\u4e86\u53d1\u51fa\u7f8e\u5999\u6b4c\u58f0\u7684\u751f\u7269\uff0c\u7adf\u7136\u662f\u4e00\u5934\u72ee\u5b50\u3002\u6b64\u65f6\uff0c\u72ee\u5b50\u8fb9\u6b4c\u5531\u8fb9\u5411\u4ed6\u4eec\u8d70\u53bb\uff0c\u4e07\u7269\u968f\u7740\u72ee\u5b50\u7684\u6b4c\u58f0\u800c\u751f\u957f\u3002","audio_info":{"audio_name":"1482824681_The Chronicles of Narnia: The Magician's Nephew_1093_0.mp3","time_list":[0,5.29,10.65,13.22,18.09,23.53,27.32,33.22,41.98,48.2,55.6,65.1,67.77,71.13,80.48,85.53,92.65,99.59,108.65,113.86,123.69,136.9,144.54,154.9,162.95,169.95,175.57,181.2,187.24,189.56,191.79,196.0,203.67,215.16,221.18,228.75,236.5,239.4,245.29,251.07,263.92,275.03,280.25,288.29,293.38,298.15,307.23,313.05,322.77,326.53,335.04,340.29,345.85,355.62,358.78,365.67,371.12,375.15,383.29,387.7,395.95,399.83,406.7,412.67,418.2,421.79,425.79,433.52,439.58,447.37,452.53,459.51,468.21,473.43,479.32,485.27,488.94,494.28,500.21,506.43,512.02,517.56,522.04,525.1,532.34,538.53],"audio_url":"http://ali.baicizhan.com/readin/audios/1482824681_The%20Chronicles%20of%20Narnia:%20The%20Magician's%20Nephew_1093_0.mp3","audio_info_by_speed":{"slow":{"audio_name":"1482826376_The Chronicles of Narnia: The Magician's Nephew_1093_1.mp3","time_list":[0,6.64,13.3,16.52,22.76,29.44,34.27,41.58,52.81,60.68,69.66,81.98,85.16,89.6,101.37,107.69,116.76,125.55,136.75,143.44,155.53,172.44,182.08,194.98,205.16,214.35,221.14,228.19,235.88,238.68,241.57,246.95,256.56,270.93,278.43,288.02,297.88,301.66,309.02,316.25,332.53,346.4,353.05,363.06,369.74,375.62,387.03,394.31,406.47,411.59,421.96,428.7,435.63,448.02,451.91,460.71,467.55,472.65,482.92,488.43,498.78,503.89,512.28,519.85,526.92,531.21,536.46,546.1,553.79,563.49,570.04,578.8,589.95,596.42,603.79,611.23,616.1,622.73,630.2,637.85,644.86,651.95,657.6,661.69,670.65,678.86],"audio_url":"http://ali.baicizhan.com/readin/audios/1482826376_The%20Chronicles%20of%20Narnia:%20The%20Magician's%20Nephew_1093_1.mp3"},"normal":{"audio_name":"1482824681_The Chronicles of Narnia: The Magician's Nephew_1093_0.mp3","time_list":[0,5.29,10.65,13.22,18.09,23.53,27.32,33.22,41.98,48.2,55.6,65.1,67.77,71.13,80.48,85.53,92.65,99.59,108.65,113.86,123.69,136.9,144.54,154.9,162.95,169.95,175.57,181.2,187.24,189.56,191.79,196.0,203.67,215.16,221.18,228.75,236.5,239.4,245.29,251.07,263.92,275.03,280.25,288.29,293.38,298.15,307.23,313.05,322.77,326.53,335.04,340.29,345.85,355.62,358.78,365.67,371.12,375.15,383.29,387.7,395.95,399.83,406.7,412.67,418.2,421.79,425.79,433.52,439.58,447.37,452.53,459.51,468.21,473.43,479.32,485.27,488.94,494.28,500.21,506.43,512.02,517.56,522.04,525.1,532.34,538.53],"audio_url":"http://ali.baicizhan.com/readin/audios/1482824681_The%20Chronicles%20of%20Narnia:%20The%20Magician's%20Nephew_1093_0.mp3"},"fast":{"audio_name":"1482827300_The Chronicles of Narnia: The Magician's Nephew_1093_2.mp3","time_list":[0,4.45,8.84,10.89,15.01,19.42,22.72,27.52,34.82,40.03,46.01,54.06,56.16,59.09,66.82,71.0,76.96,82.68,90.23,94.5,102.5,113.67,119.99,128.52,135.32,140.94,145.75,150.34,155.29,157.24,159.19,162.7,169.14,178.66,183.57,189.8,196.32,198.71,203.53,208.3,219.1,228.3,232.59,239.14,243.49,247.41,254.98,259.82,267.78,270.97,277.96,282.47,286.95,295.17,297.69,303.52,307.94,311.36,318.01,321.76,328.62,331.82,337.43,342.46,347.08,349.93,353.43,359.56,364.8,371.26,375.54,381.32,388.65,392.91,397.85,402.67,405.83,410.2,415.07,420.32,424.75,429.44,433.28,435.89,441.83,447.05],"audio_url":"http://ali.baicizhan.com/readin/audios/1482827300_The%20Chronicles%20of%20Narnia:%20The%20Magician's%20Nephew_1093_2.mp3"}}},"words_count":1315,"paragraph":[],"share_words":"It made you want to run and jump and climb. It made you want to shoot. It made you want to rush at other people and either hug them or fight them.","title_en":"*CHAPTER 17","article_title":"Chapter 17"},"problem_info":[{"question":{"cn":"\u5973\u5deb\u6254\u5411\u72ee\u5b50\u7684\u94c1\u68d2\u51fb\u4e2d\u4e86\u72ee\u5b50\u5417\uff1f","en":"Did the iron bar that the witch threw hit the Lion?"},"options":[{"cn":"\u662f\u7684\uff0c\u51fb\u4e2d\u4e86\u3002","en":"Yes, it did."},{"cn":"\u4e0d\uff0c\u6ca1\u51fb\u4e2d\u3002","en":"No, it didn't."},{"cn":"\u4e0d\u77e5\u9053\u3002","en":"We don\u2019t know."}],"answer":[0],"analysis":["\u6587\u4e2d\u63d0\u5230\uff1a\u201cThe bar struck the Lion fair between the eyes. It glanced off and fell with a thud in the grass.\u201d\u7531\u6b64\u53ef\u77e5\u5973\u5deb\u6254\u5411\u72ee\u5b50\u7684\u94c1\u68d2\u51fb\u4e2d\u4e86\u72ee\u5b50\uff0c\u4f46\u662f\u72ee\u5b50\u5bf9\u6b64\u6ca1\u6709\u5728\u610f\uff0c\u56e0\u6b64\u9009A\u3002"]},{"question":{"cn":"\u8c01\u88ab\u6811\u6839\u7eca\u5012\u5e76\u6454\u5728\u4e86\u6cb3\u91cc\uff1f","en":"Who tripped over a root and fell down into the river?"},"options":[{"cn":"\u5973\u5deb\u3002","en":"The Witch."},{"cn":"\u72ee\u5b50\u3002","en":"The Lion."},{"cn":"Uncle Andrew\u3002","en":"Uncle Andrew."}],"answer":[2],"analysis":["\u6587\u4e2d\u63d0\u5230\uff1a\u201cUncle Andrew turned to do likewise, tripped over a root, and fell flat on his face in a little brook that ran down to join the river.\u201d\u7531\u6b64\u53ef\u77e5\uff0c\u5728\u9003\u8dd1\u7684\u8fc7\u7a0b\u4e2d\u88ab\u6811\u6839\u7eca\u5012\u8dcc\u8fdb\u6c34\u91cc\u7684\u662fUncle Andrew\uff0c\u56e0\u6b64\u9009C\u3002"]},{"question":{"cn":"\u5f53Polly\u548cUncle Andrew\u6765\u5230Digory\u65c1\u8fb9\uff0c\u4ed6\u4eec\u770b\u89c1\u4e86\u4ec0\u4e48\uff1f","en":"When Polly and Uncle Andrew came to Digory\u2019s side, what did they see?"},"options":[{"cn":"\u4e00\u4e2a\u706f\u67f1\u3002","en":"A lamp-post."},{"cn":"\u4e00\u9897\u82f9\u679c\u3002","en":"An apple tree."},{"cn":"\u4e00\u53ea\u9e1f\u3002","en":"A bird."}],"answer":[0],"analysis":["\u6587\u4e2d\u63d0\u5230\uff1a\u201cBut when he saw what Digory was looking at, even he began to take an interest. It was a perfect little model of a lamp-post. . . \u201d\u7531\u6b64\u5f97\u77e5\uff0c\u4ed6\u4eec\u770b\u89c1\u4e86\u4e00\u4e2a\u5c0f\u578b\u706f\u67f1\uff0c\u56e0\u6b64\u9009A\u3002"]},{"question":{"cn":"\u6839\u636eDigory\u7684\u53d9\u8ff0\uff0c\u706f\u67f1\u662f\u4ece\u54ea\u91cc\u6765\u7684\uff1f","en":"According to Digory, where did this lamp-post come from?"},"options":[{"cn":"\u6765\u81ea\u73b0\u5b9e\u4e16\u754c\u3002","en":"It came from the real world."},{"cn":"\u6765\u81ea\u6811\u6797\u3002","en":"It came from the woods."},{"cn":"\u6765\u81ea\u9b54\u6cd5\u4e16\u754c\u3002","en":"It came from the magic world."}],"answer":[0],"analysis":["\u6587\u4e2d\u63d0\u5230\uff1a\u201cThis is where the bar fell- the bar she tore off the lamp-post at home. It sank into the ground and now it\u2019s coming up as a young lamp-post.\u201d\u7531\u6b64\u53ef\u77e5\uff0c\u5973\u5deb\u4ece\u73b0\u5b9e\u4e16\u754c\u626d\u4e0b\u6765\u7684\u94c1\u68d2\u6389\u8fdb\u571f\u91cc\uff0c\u8fd9\u6839\u94c1\u68d2\u957f\u6210\u4e86\u4e00\u4e2a\u706f\u67f1\uff0c\u56e0\u6b64\u9009A\u3002"]},{"question":{"cn":"\u4e3a\u4ec0\u4e48Uncle Andrew\u8ba4\u4e3a\u8fd9\u4e2a\u5730\u65b9\u5145\u6ee1\u4e86\u5546\u4e1a\u6f5c\u529b\uff1f","en":"Why did Uncle Andrew think that this place was full of commercial possibilities?"},"options":[{"cn":"\u56e0\u4e3a\u4ed6\u53ef\u4ee5\u5c06\u8fd9\u91cc\u7684\u65b0\u9c9c\u7a7a\u6c14\u548c\u6811\u6728\u5356\u5f80\u73b0\u5b9e\u4e16\u754c\u3002","en":"Because he could sell the fresh air and trees here to the real world."},{"cn":"\u56e0\u4e3a\u4ed6\u53ef\u4ee5\u5728\u8fd9\u91cc\u57cb\u4e0b\u4e00\u4e9b\u788e\u7247\u7136\u540e\u6536\u83b7\u5b8c\u6574\u7684\u7269\u4ef6\u3002","en":"Because he could bury some scraps here and then harvest complete things."},{"cn":"\u56e0\u4e3a\u4ed6\u53ef\u4ee5\u5728\u8fd9\u91cc\u57cb\u4e0b\u4e00\u4e9b\u7eb8\u5e01\u7136\u540e\u6536\u83b7\u6570\u4e0d\u6e05\u7684\u94b1\u3002","en":"Because he could bury some bank notes here and then harvest countless money."}],"answer":[1],"analysis":["\u6587\u4e2d\u63d0\u5230\uff1a\u201cBring a few old bits of scrap iron here, bury them, and up they come as brand new railway engines, battleships, anything you please. They\u2019ll cost nothing, and I can sell them at full prices in England.\u201d\u8bf4\u660eUncle Andrew\u60f3\u7740\u628a\u7269\u4f53\u7684\u788e\u7247\u57cb\u5728\u8fd9\u91cc\u6536\u83b7\u5b8c\u6574\u7684\u7269\u4ef6\u518d\u53bb\u5356\u6389\uff0c\u6240\u4ee5\u9009B\u3002"]}],"book_cover_img_url":"http://ali.baicizhan.com/readin/images/Cover-The-Magician-Nephew.png","book_show_img_url":"http://ali.baicizhan.com/readin/images/Narnia-2.png","share_img_url":"http://ali.baicizhan.com/readin/images/Cover_MagiciansNephew.png","current_chapter":17,"book_name":"The Magician\u2019s Nephew","book_name_cn":"\u9b54\u6cd5\u5e08\u7684\u5916\u7525","bid":17,"total_words_of_term":116388,"user_submit":[1,1,1,1,1],"is_term_finish":false,"term_start_day":"2017-10-16","share_title":"100\u5929\u8bfb\u5b8c4\u672c\u82f1\u6587\u4e66\uff0c\u4eca\u5929\u662f\u7b2c32\u5929","teacher_notes_url":"http://reading.baicizhan.com/article/83c6954ebf0e2dcb46480a725724675b","current_learn_day":32,"learn_book_count":4}